doc/make_index.py
doc/img/penguins_screenshot_01.png
doc/img/penguins_screenshot_02.png
doc/img/penguins_screenshot_03.png
doc/pub_doc/api_versions.txt
doc/pub_doc/index.html
doc/pub_doc/index_warp.html
doc/pub_doc/archive/.retain
rendu/__init__.py
rendu/htmldeck.py
rendu/render/render_scripts.js
rendu/render/render_styles.css
rendu-0.1.2.dist-info/licenses/LICENSE
test/penguins_example.py
rendu-0.1.2.dist-info/METADATA
rendu-0.1.2.dist-info/WHEEL
rendu-0.1.2.dist-info/top_level.txt
rendu-0.1.2.dist-info/RECORD
