Metadata-Version: 2.4
Name: rendu
Version: 0.1.2
Summary: A library to programmatically create presentation slide decks
Author-email: Mattia Borsalino <mattia.borsalino@gmail.com>
License-Expression: MIT
Project-URL: Homepage, https://github.com/mborsalino/rendu
Project-URL: Repository, https://github.com/mborsalino/rendu.git
Keywords: presentation,report,slide,powerpoint,keynote
Classifier: Programming Language :: Python :: 3
Classifier: Operating System :: OS Independent
Requires-Python: >=3.7.4
License-File: LICENSE
Dynamic: license-file
